setup.cfg
setup.py
django_futures/__init__.py
django_futures/audit.py
django_futures/decorators.py
django_futures/http_client.py
django_futures.egg-info/PKG-INFO
django_futures.egg-info/SOURCES.txt
django_futures.egg-info/dependency_links.txt
django_futures.egg-info/requires.txt
django_futures.egg-info/top_level.txt
django_futures/core/__init__.py
django_futures/core/exceptions.py
django_futures/core/handlers/__init__.py
django_futures/core/handlers/application.py
django_futures/core/handlers/df.py
django_futures/core/handlers/df_staticfiles.py
django_futures/core/handlers/tv32/__init__.py
django_futures/core/handlers/tv32/application.py
django_futures/core/handlers/tv32/df.py
django_futures/core/handlers/tv40/__init__.py
django_futures/core/handlers/tv40/application.py
django_futures/core/handlers/tv40/df.py
django_futures/management/__init__.py
django_futures/management/commands/__init__.py
django_futures/management/commands/run_tornado.py