Metadata-Version: 1.0
Name: django-futures
Version: 0.1.0.dev1
Summary: Django asynchronous views and Tornado integration made easy.
Home-page: UNKNOWN
Author: Jeff Buttars
Author-email: jeffbuttars@gmail.com
License: MIT
Platform: UNKNOWN
